approx_umap/__init__.py
approx_umap/approx_aligned_umap.py
approx_umap/approx_umap.py
approx_umap/functions.py
approx_umap/temp.py
approx_umap-0.3.0.dist-info/LICENSE
approx_umap-0.3.0.dist-info/METADATA
approx_umap-0.3.0.dist-info/WHEEL
approx_umap-0.3.0.dist-info/RECORD
