Metadata-Version: 2.1
Name: approx-umap
Version: 0.3.0
Summary: Modification of the UMAP algorithm to allow for fast approximate projections of new data points.
Home-page: https://github.com/PierreGtch/approx-umap
License: BSD-3-Clause
Author: Pierre Guetschel
Author-email: pierre.guetschel@donders.ru.nl
Requires-Python: >=3.10,<3.13
Classifier: License :: OSI Approved :: BSD License
Classifier: Programming Language :: Python :: 3
Classifier: Programming Language :: Python :: 3.10
Classifier: Programming Language :: Python :: 3.11
Requires-Dist: docstring-inheritance (>=2.2.0,<3.0.0)
Requires-Dist: umap-learn (>=0.5.5,<0.6.0)
Project-URL: Repository, https://github.com/PierreGtch/approx-umap
